victor/MarkdownDocument.py
victor/MarkdownRenderer.py
victor/__init__.py
victor/__main__.py
victor/build.py
victor/help.py
victor/init.py
victor/new.py
victor/serve.py
victor/CONSTANTS/__init__.py
victor/CONSTANTS/config.py
victor/CONSTANTS/directories.py
victor/CONSTANTS/environment.py
victor/CONSTANTS/regex.py
victor/assets/stylesheets/projects.css
victor/assets/stylesheets/syntax_highlight.css
victor/assets/stylesheets/victor.css
victor/assets/stylesheets/font-awesome-4.7.0/HELP-US-OUT.txt
victor/assets/stylesheets/font-awesome-4.7.0/css/font-awesome.css
victor/assets/stylesheets/font-awesome-4.7.0/css/font-awesome.min.css
victor/assets/stylesheets/font-awesome-4.7.0/fonts/FontAwesome.otf
victor/assets/stylesheets/font-awesome-4.7.0/fonts/fontawesome-webfont.eot
victor/assets/stylesheets/font-awesome-4.7.0/fonts/fontawesome-webfont.svg
victor/assets/stylesheets/font-awesome-4.7.0/fonts/fontawesome-webfont.ttf
victor/assets/stylesheets/font-awesome-4.7.0/fonts/fontawesome-webfont.woff
victor/assets/stylesheets/font-awesome-4.7.0/fonts/fontawesome-webfont.woff2
victor/assets/stylesheets/font-awesome-4.7.0/less/animated.less
victor/assets/stylesheets/font-awesome-4.7.0/less/bordered-pulled.less
victor/assets/stylesheets/font-awesome-4.7.0/less/core.less
victor/assets/stylesheets/font-awesome-4.7.0/less/fixed-width.less
victor/assets/stylesheets/font-awesome-4.7.0/less/font-awesome.less
victor/assets/stylesheets/font-awesome-4.7.0/less/icons.less
victor/assets/stylesheets/font-awesome-4.7.0/less/larger.less
victor/assets/stylesheets/font-awesome-4.7.0/less/list.less
victor/assets/stylesheets/font-awesome-4.7.0/less/mixins.less
victor/assets/stylesheets/font-awesome-4.7.0/less/path.less
victor/assets/stylesheets/font-awesome-4.7.0/less/rotated-flipped.less
victor/assets/stylesheets/font-awesome-4.7.0/less/screen-reader.less
victor/assets/stylesheets/font-awesome-4.7.0/less/stacked.less
victor/assets/stylesheets/font-awesome-4.7.0/less/variables.less
victor_ssg-0.0.9.dist-info/LICENSE
victor_ssg-0.0.9.dist-info/METADATA
victor_ssg-0.0.9.dist-info/WHEEL
victor_ssg-0.0.9.dist-info/top_level.txt
victor_ssg-0.0.9.dist-info/RECORD
