Metadata-Version: 2.1
Name: victor-ssg
Version: 0.0.9
Summary: A static site generator for use on my blog
Home-page: https://github.com/LukeBriggsDev/victorssg
Author: Luke Briggs
Author-email: contact@lukebriggs.dev
License: UNKNOWN
Project-URL: Bug Tracker, https://github.com/LukeBriggsDev/victorssg
Platform: UNKNOWN
Classifier: Programming Language :: Python :: 3
Classifier: License :: OSI Approved :: MIT License
Classifier: Operating System :: OS Independent
Requires-Python: >=3.6
License-File: LICENSE
Requires-Dist: Jinja2
Requires-Dist: pyyaml
Requires-Dist: mistune (==2.0.0rc1)
Requires-Dist: regex
Requires-Dist: pygments
Requires-Dist: feedgen
